[{"name":"test","id":1,"email":"test@test.com","password":"test","projects":[{"name":"Project 2","id":2,"files":[{"name":"","desc":"asdadsasddas","classes":[{"name":"asdasdasd","desc":"asdasdasd","methods":[{"name":"sadsad","rety":"sadads","args":"asdasd","desc":"asdadsasd"}],"props":[{"name":"asdasd","type":"public-property"},{"name":"asddasasddas","type":"public-property"}]}]},{"name":"asdasdads","desc":"adsdasadsdas","classes":[{"name":"adsasdasdasd","desc":"asdadsasd","methods":[{"name":"asddasads","rety":"asdasdasd","args":"asdasdasd","desc":"asdasasd"}],"props":[{"name":"asdsdaads","type":"public-property"}]}]}]},{"name":"Project 1","id":"1","files":[{"name":"asdads","desc":"asdads","classes":[{"name":"sadadsdsa","desc":"asdasd","methods":[],"props":[]}]}]},{"name":"Project 3","id":3,"files":[{"name":"","desc":"","classes":[{"methods":[],"props":[]}]}]}]}]